pytest_async_sqlalchemy.py
pytest_async_sqlalchemy-0.2.0.dist-info/LICENSE
pytest_async_sqlalchemy-0.2.0.dist-info/METADATA
pytest_async_sqlalchemy-0.2.0.dist-info/WHEEL
pytest_async_sqlalchemy-0.2.0.dist-info/entry_points.txt
pytest_async_sqlalchemy-0.2.0.dist-info/top_level.txt
pytest_async_sqlalchemy-0.2.0.dist-info/RECORD
