Metadata-Version: 2.1
Name: pytest-async-sqlalchemy
Version: 0.2.0
Summary: Database testing fixtures using the SQLAlchemy asyncio API
Home-page: https://github.com/igortg/pytest-async-sqlalchemy
Author: Igor T. Ghisi
Author-email: igor.ghisi@gmail.com
Maintainer: Igor T. Ghisi
Maintainer-email: igor.ghisi@gmail.com
License: MIT
Platform: UNKNOWN
Classifier: Development Status :: 4 - Beta
Classifier: Framework :: Pytest
Classifier: Intended Audience :: Developers
Classifier: Topic :: Software Development :: Testing
Classifier: Programming Language :: Python
Classifier: Programming Language :: Python :: 3
Classifier: Programming Language :: Python :: 3.5
Classifier: Programming Language :: Python :: 3.6
Classifier: Programming Language :: Python :: 3.7
Classifier: Programming Language :: Python :: 3.8
Classifier: Programming Language :: Python :: 3 :: Only
Classifier: Programming Language :: Python :: Implementation :: CPython
Classifier: Programming Language :: Python :: Implementation :: PyPy
Classifier: Operating System :: OS Independent
Classifier: License :: OSI Approved :: MIT License
Requires-Python: >=3.6
License-File: LICENSE
Requires-Dist: pytest (>=6.0.0)
Requires-Dist: sqlalchemy (>=1.4.0)
